flyteplugins/pytorch/__init__.py
flyteplugins/pytorch/task.py
flyteplugins_pytorch-2.0.0b53.dist-info/METADATA
flyteplugins_pytorch-2.0.0b53.dist-info/WHEEL
flyteplugins_pytorch-2.0.0b53.dist-info/top_level.txt
flyteplugins_pytorch-2.0.0b53.dist-info/RECORD
