Metadata-Version: 2.4
Name: flyteplugins-pytorch
Version: 2.0.0b53
Summary: pytorch plugin for flyte
Author-email: Kevin Liao <kevinliao852@users.noreply.github.com>
Requires-Python: >=3.10
Requires-Dist: torch
Requires-Dist: flyte
